easy_django_csv/__init__.py
easy_django_csv/exporters.py
easy_django_csv-0.1.5.dist-info/licenses/LICENSE
easy_django_csv-0.1.5.dist-info/METADATA
easy_django_csv-0.1.5.dist-info/WHEEL
easy_django_csv-0.1.5.dist-info/top_level.txt
easy_django_csv-0.1.5.dist-info/RECORD
