Metadata-Version: 2.4
Name: easy_django_csv
Version: 0.1.5
Summary: Simple CSV export for Django
Home-page: https://github.com/alex-dicko/Easy-Django-CSV
Author: Alex Dickens
Author-email: alex@calmdigital.com
Classifier: Framework :: Django
Classifier: Programming Language :: Python :: 3
Classifier: License :: OSI Approved :: MIT License
Requires-Python: >=3.8
License-File: LICENSE
Requires-Dist: Django>=3.2
Dynamic: author
Dynamic: author-email
Dynamic: classifier
Dynamic: description
Dynamic: description-content-type
Dynamic: home-page
Dynamic: license-file
Dynamic: requires-dist
Dynamic: requires-python
Dynamic: summary
